secapi_tl/__init__.py
secapi_tl/request.py
secapi_tl/submission.py
secapi_tl/submission_query.py
secapi_tl/utility_functions.py
secapi_tl-1.2.3.dist-info/LICENSE
secapi_tl-1.2.3.dist-info/METADATA
secapi_tl-1.2.3.dist-info/WHEEL
secapi_tl-1.2.3.dist-info/top_level.txt
secapi_tl-1.2.3.dist-info/RECORD
