Metadata-Version: 2.1
Name: secapi-tl
Version: 1.2.3
License: MIT License
Project-URL: Homepage, https://github.com/tlie03/secapi
Requires-Python: >=2.7.18
License-File: LICENSE
Requires-Dist: typing
Requires-Dist: ratelimiter
Requires-Dist: requests
Requires-Dist: openDateRange
